cors/__init__.py
cors/definitions.py
cors/errors.py
cors/preflight.py
cors/utils.py
cors/version.py
cors/clients/__init__.py
cors/clients/requests.py
cors/clients/tornado.py
cors.testing-0.4.0.dist-info/LICENSE
cors.testing-0.4.0.dist-info/METADATA
cors.testing-0.4.0.dist-info/WHEEL
cors.testing-0.4.0.dist-info/top_level.txt
cors.testing-0.4.0.dist-info/RECORD
