Metadata-Version: 2.1
Name: cors.testing
Version: 0.4.0
Summary: Utilities for creating CORS-enabled HTTP interfaces
Home-page: https://github.com/bendikro/python-cors
Author: Nick Coutsos
Author-email: ncoutsos@synacor.com
License: UNKNOWN
Platform: UNKNOWN
Classifier: Development Status :: 4 - Beta
Classifier: Programming Language :: Python :: 2.7
Classifier: Programming Language :: Python :: 3
Classifier: License :: OSI Approved :: GNU General Public License v3 (GPLv3)
Classifier: Operating System :: OS Independent
Classifier: Topic :: Internet :: WWW/HTTP
Classifier: Topic :: Software Development :: Libraries :: Python Modules
Classifier: Topic :: Software Development :: Testing :: Unit
Requires-Dist: future
Requires-Dist: requests
Requires-Dist: tornado
